[
  {
    "name": "Ever Alot",
    "loop": "LL6",
    "port": "NGB",
    "etd": "17-Dec",
    "eta": "24-Jan",
    "weekNum": 51,
    "allocation": 10,
    "id": "vessel-1"
  },
  {
    "name": "Ever Alot",
    "loop": "LL6",
    "port": "YTN",
    "etd": "21-Dec",
    "eta": "24-Jan",
    "weekNum": 51,
    "allocation": 6,
    "id": "vessel-2"
  },
  {
    "name": "Ever Atop",
    "loop": "LL6",
    "port": "NGB",
    "etd": "24-Dec",
    "eta": "28-Jan",
    "weekNum": 52,
    "allocation": 10,
    "id": "vessel-3"
  },
  {
    "name": "Ever Atop",
    "loop": "LL6",
    "port": "YTN",
    "etd": "28-Dec",
    "eta": "28-Jan",
    "weekNum": 52,
    "allocation": 6,
    "id": "vessel-4"
  },
  {
    "name": "COSCO FRANCE",
    "loop": "LL3",
    "port": "YTN",
    "etd": "20-Dec",
    "eta": "23-Jan",
    "weekNum": 51,
    "allocation": 5,
    "id": "vessel-5"
  },
  {
    "name": "OOCL MALAYSIA",
    "loop": "LL3",
    "port": "YTN",
    "etd": "30-Dec",
    "eta": "30-Jan",
    "weekNum": 53,
    "allocation": 5,
    "id": "vessel-6"
  },
  {
    "name": "COSCO EXCELLENCE",
    "loop": "LL3",
    "port": "YTN",
    "etd": "20-Dec",
    "eta": "23-Jan",
    "weekNum": 51,
    "allocation": 5,
    "id": "vessel-7"
  },
  {
    "name": "CMA CGM VENDOME",
    "loop": "LL5",
    "port": "NGB",
    "etd": "22-Dec",
    "eta": "31-Jan",
    "weekNum": 51,
    "allocation": 4,
    "id": "vessel-8"
  },
  {
    "name": "Ever Greet",
    "loop": "LL6",
    "port": "NGB",
    "etd": "31-Dec",
    "eta": "4-Feb",
    "weekNum": 53,
    "allocation": 10,
    "id": "vessel-9"
  },
  {
    "name": "Ever Greet",
    "loop": "LL6",
    "port": "YTN",
    "etd": "4-Jan",
    "eta": "4-Feb",
    "weekNum": 1,
    "allocation": 6,
    "id": "vessel-10"
  },
  {
    "name": "MSC Aurora",
    "loop": "LL2",
    "port": "NGB",
    "etd": "6-Jan",
    "eta": "12-Feb",
    "weekNum": 2,
    "allocation": 8,
    "id": "vessel-11"
  },
  {
    "name": "MSC Aurora",
    "loop": "LL2",
    "port": "YTN",
    "etd": "8-Jan",
    "eta": "12-Feb",
    "weekNum": 2,
    "allocation": 5,
    "id": "vessel-12"
  },
  {
    "name": "Hapag Lloyd",
    "loop": "LL4",
    "port": "NGB",
    "etd": "10-Jan",
    "eta": "15-Feb",
    "weekNum": 2,
    "allocation": 7,
    "id": "vessel-13"
  },
  {
    "name": "Hapag Lloyd",
    "loop": "LL4",
    "port": "YTN",
    "etd": "12-Jan",
    "eta": "15-Feb",
    "weekNum": 2,
    "allocation": 5,
    "id": "vessel-14"
  },
  {
    "name": "ONE Horizon",
    "loop": "LL1",
    "port": "NGB",
    "etd": "14-Jan",
    "eta": "18-Feb",
    "weekNum": 3,
    "allocation": 9,
    "id": "vessel-15"
  },
  {
    "name": "ONE Horizon",
    "loop": "LL1",
    "port": "YTN",
    "etd": "15-Jan",
    "eta": "18-Feb",
    "weekNum": 3,
    "allocation": 4,
    "id": "vessel-16"
  },
  {
    "name": "Maersk Stella",
    "loop": "LL3",
    "port": "NGB",
    "etd": "17-Jan",
    "eta": "21-Feb",
    "weekNum": 3,
    "allocation": 6,
    "id": "vessel-17"
  },
  {
    "name": "Maersk Stella",
    "loop": "LL3",
    "port": "YTN",
    "etd": "19-Jan",
    "eta": "21-Feb",
    "weekNum": 3,
    "allocation": 5,
    "id": "vessel-18"
  },
  {
    "name": "ZIM Polaris",
    "loop": "LL5",
    "port": "NGB",
    "etd": "21-Jan",
    "eta": "26-Feb",
    "weekNum": 4,
    "allocation": 7,
    "id": "vessel-19"
  },
  {
    "name": "ZIM Polaris",
    "loop": "LL5",
    "port": "YTN",
    "etd": "23-Jan",
    "eta": "26-Feb",
    "weekNum": 4,
    "allocation": 6,
    "id": "vessel-20"
  }
]
